setup.py
clip_client/__init__.py
clip_client/client.py
clip_client/helper.py
clip_client.egg-info/PKG-INFO
clip_client.egg-info/SOURCES.txt
clip_client.egg-info/dependency_links.txt
clip_client.egg-info/not-zip-safe
clip_client.egg-info/requires.txt
clip_client.egg-info/top_level.txt