Metadata-Version: 2.1
Name: clip-client
Version: 0.4.20
Summary: Embed images and sentences into fixed-length vectors via CLIP
Home-page: https://github.com/jina-ai/clip-as-service
Author: Jina AI
Author-email: hello@jina.ai
License: Apache 2.0
Download-URL: https://github.com/jina-ai/clip-as-service/tags
Project-URL: Documentation, https://clip-as-service.jina.ai
Project-URL: Source, https://github.com/jina-ai/clip-as-service/
Project-URL: Tracker, https://github.com/jina-ai/clip-as-service/issues
Keywords: jina openai clip deep-learning cross-modal multi-modal neural-search
Platform: UNKNOWN
Classifier: Development Status :: 5 - Production/Stable
Classifier: Intended Audience :: Developers
Classifier: Intended Audience :: Education
Classifier: Intended Audience :: Science/Research
Classifier: Programming Language :: Python :: 3.7
Classifier: Programming Language :: Python :: 3.8
Classifier: Programming Language :: Python :: 3.9
Classifier: Programming Language :: Python :: 3.10
Classifier: Programming Language :: Unix Shell
Classifier: Environment :: Console
Classifier: License :: OSI Approved :: Apache Software License
Classifier: Operating System :: OS Independent
Classifier: Topic :: Database :: Database Engines/Servers
Classifier: Topic :: Scientific/Engineering :: Artificial Intelligence
Classifier: Topic :: Internet :: WWW/HTTP :: Indexing/Search
Classifier: Topic :: Scientific/Engineering :: Image Recognition
Classifier: Topic :: Multimedia :: Video
Classifier: Topic :: Scientific/Engineering
Classifier: Topic :: Scientific/Engineering :: Mathematics
Classifier: Topic :: Software Development
Classifier: Topic :: Software Development :: Libraries
Classifier: Topic :: Software Development :: Libraries :: Python Modules
Provides-Extra: test
